deskaone_sdk_api/__init__.py
deskaone_sdk_api/Client/__init__.py
deskaone_sdk_api/Database/__init__.py
deskaone_sdk_api/Exceptions/__init__.py
deskaone_sdk_api/Internal/__init__.py
deskaone_sdk_api/Utils/__init__.py
deskaone_sdk_api/Utils/AWSViker.py
deskaone_sdk_api/Utils/Color.py
deskaone_sdk_api/Utils/Crypto.py
deskaone_sdk_api/Utils/ProgressBar.py
deskaone_sdk_api/Utils/Proxy.py
deskaone_sdk_api/Utils/Random.py
deskaone_sdk_api/Utils/Reset.py
deskaone_sdk_api/Utils/Reverse.py
deskaone_sdk_api/Utils/Timer.py
deskaone_sdk_api/Utils/Typer.py
deskaone_sdk_api/Utils/UserAgent.py
deskaone_sdk_api-0.0.5.dist-info/WHEEL
deskaone_sdk_api-0.0.5.dist-info/METADATA
deskaone_sdk_api-0.0.5.dist-info/RECORD
