Metadata-Version: 2.1
Name: deskaone-sdk-api
Version: 0.0.5
Summary: 
Author: DesKaOne
Requires-Python: >=3.8,<4.0
Classifier: Programming Language :: Python :: 3
Classifier: Programming Language :: Python :: 3.8
Classifier: Programming Language :: Python :: 3.9
Classifier: Programming Language :: Python :: 3.10
Classifier: Programming Language :: Python :: 3.11
Requires-Dist: base58 (>=2.1.1,<3.0.0)
Requires-Dist: bs4 (>=0.0.1,<0.0.2)
Requires-Dist: colorama (>=0.4.5,<0.5.0)
Requires-Dist: flask (>=2.2.3,<3.0.0)
Requires-Dist: gunicorn (>=20.1.0,<21.0.0)
Requires-Dist: html5lib (>=1.1,<2.0)
Requires-Dist: install-jdk (>=0.3.0,<0.4.0)
Requires-Dist: polling (>=0.3.2,<0.4.0)
Requires-Dist: polling2 (>=0.5.0,<0.6.0)
Requires-Dist: pycryptodome (>=3.17,<4.0)
Requires-Dist: pysocks (>=1.7.1,<2.0.0)
Requires-Dist: python-dotenv (>=0.21.0,<0.22.0)
Requires-Dist: random-user-agent (>=1.0.1,<2.0.0)
Requires-Dist: requests[socks] (>=2.27.1,<3.0.0)
Requires-Dist: sqlalchemy (==1.4.29)
